latex_runner/__init__.py
latex_runner/__main__.py
latex_runner/about.py
latex_runner/config_types.py
latex_runner/main.py
latex_runner/py.typed
latex_runner/runmodule.sh
latex_runner-1.2.0.dist-info/entry_points.txt
latex_runner-1.2.0.dist-info/licenses/LICENSE
latex_runner-1.2.0.dist-info/WHEEL
latex_runner-1.2.0.dist-info/METADATA
latex_runner-1.2.0.dist-info/RECORD
