Metadata-Version: 2.4
Name: latex-runner
Version: 1.2.0
Summary: Build a LaTeX file.
Author-email: erzo <erzo@posteo.de>
Requires-Python: >=3.8
Classifier: Operating System :: POSIX
Classifier: Operating System :: Unix
Classifier: Operating System :: MacOS
Classifier: Operating System :: Microsoft :: Windows
Classifier: Environment :: Console
Classifier: License :: OSI Approved :: BSD License
Classifier: Typing :: Typed
License-File: LICENSE
Requires-Dist: confattr >= 1.4.0, < 2
Requires-Dist: colorama
Project-URL: Bug tracker, https://gitlab.com/erzo/latex-runner/-/issues
Project-URL: Change log, https://gitlab.com/erzo/latex-runner/-/tags
Project-URL: Documentation, https://erzo.gitlab.io/latex-runner/latest
Project-URL: Source code, https://gitlab.com/erzo/latex-runner
